nassemble/__init__.py
nassemble/main.py
nassemble-1.0.0.dist-info/licenses/LICENSE
nassemble-1.0.0.dist-info/METADATA
nassemble-1.0.0.dist-info/WHEEL
nassemble-1.0.0.dist-info/entry_points.txt
nassemble-1.0.0.dist-info/top_level.txt
nassemble-1.0.0.dist-info/RECORD
